socx/__init__.py
socx/socx.py
socx/util.py
socx-2.3.dist-info/METADATA
socx-2.3.dist-info/WHEEL
socx-2.3.dist-info/entry_points.txt
socx-2.3.dist-info/top_level.txt
socx-2.3.dist-info/RECORD
