Metadata-Version: 2.4
Name: socx
Version: 2.3
Summary: A set of useful tools for a security operations center
Author-email: Enlace <enlace.aman@gmail.com>
Classifier: Programming Language :: Python :: 3
Classifier: Operating System :: OS Independent
Requires-Python: >=3.8
